sqlite_shift/__init__.py
sqlite_shift/base_migration.py
sqlite_shift/cli.py
sqlite_shift/manager.py
tests/__init__.py
tests/conftest.py
tests/test_manager.py
tests/schema_migrations/001_initial.py
tests/schema_migrations/002_add_foriegn_key.py
tests/schema_migrations/__init__.py
sqlite_shift-0.2.0.dist-info/LICENSE
sqlite_shift-0.2.0.dist-info/METADATA
sqlite_shift-0.2.0.dist-info/WHEEL
sqlite_shift-0.2.0.dist-info/entry_points.txt
sqlite_shift-0.2.0.dist-info/top_level.txt
sqlite_shift-0.2.0.dist-info/RECORD
