Metadata-Version: 2.1
Name: sqlite-shift
Version: 0.2.0
Summary: A framework for managing SQLite database migrations, inspired by Django.
Home-page: https://github.com/Akarsh-TS/sqlite-shift
Author: Akarsh T S
Author-email: ts.akarsh@gmail.com
License: Apache License 2.0
Platform: UNKNOWN
Classifier: Development Status :: 4 - Beta
Classifier: Intended Audience :: Developers
Classifier: Topic :: Database
Classifier: Programming Language :: Python :: 3
Classifier: License :: OSI Approved :: Apache Software License
Classifier: Operating System :: OS Independent
Requires-Python: >=3.6
License-File: LICENSE
Requires-Dist: click
